pyqstrat/__init__.py
pyqstrat/account.py
pyqstrat/evaluator.py
pyqstrat/holiday_calendars.py
pyqstrat/marketdata_processor.py
pyqstrat/optimize.py
pyqstrat/orders.py
pyqstrat/plot.py
pyqstrat/portfolio.py
pyqstrat/pq_types.py
pyqstrat/pq_utils.py
pyqstrat/pyqstrat_cpp.cpython-37m-darwin.so
pyqstrat/strategy.py
pyqstrat/trade_bars.py
pyqstrat/version.py
pyqstrat/cpp/aggregators.cpp
pyqstrat/cpp/aggregators.hpp
pyqstrat/cpp/arrow_writer.cpp
pyqstrat/cpp/arrow_writer.hpp
pyqstrat/cpp/date.hpp
pyqstrat/cpp/options.cpp
pyqstrat/cpp/options.hpp
pyqstrat/cpp/pq_types.hpp
pyqstrat/cpp/py_import_call_execute.cpp
pyqstrat/cpp/py_import_call_execute.hpp
pyqstrat/cpp/pybind.cpp
pyqstrat/cpp/pybind_options.cpp
pyqstrat/cpp/tests.cpp
pyqstrat/cpp/text_file_parsers.cpp
pyqstrat/cpp/text_file_parsers.hpp
pyqstrat/cpp/text_file_processor.cpp
pyqstrat/cpp/text_file_processor.hpp
pyqstrat/cpp/utils.cpp
pyqstrat/cpp/utils.hpp
pyqstrat/cpp/lets_be_rational/erf_cody.cpp
pyqstrat/cpp/lets_be_rational/importexport.h
pyqstrat/cpp/lets_be_rational/lets_be_rational.cpp
pyqstrat/cpp/lets_be_rational/normaldistribution.cpp
pyqstrat/cpp/lets_be_rational/normaldistribution.h
pyqstrat/cpp/lets_be_rational/rationalcubic.cpp
pyqstrat/cpp/lets_be_rational/rationalcubic.h
pyqstrat/notebooks/building_strategies.ipynb
pyqstrat/notebooks/optimizing_strategies.ipynb
pyqstrat/notebooks/options_trading.ipynb
pyqstrat/notebooks/pair_trading_strategy.ipynb
pyqstrat/notebooks/processing_marketdata_files.ipynb
pyqstrat/notebooks/reporting_and_plotting.ipynb
pyqstrat/notebooks/.ipynb_checkpoints/building_strategies-checkpoint.ipynb
pyqstrat/notebooks/.ipynb_checkpoints/optimizing_strategies-checkpoint.ipynb
pyqstrat/notebooks/.ipynb_checkpoints/options_trading-checkpoint.ipynb
pyqstrat/notebooks/.ipynb_checkpoints/pair_trading_strategy-checkpoint.ipynb
pyqstrat/notebooks/.ipynb_checkpoints/processing_marketdata_files-checkpoint.ipynb
pyqstrat/notebooks/.ipynb_checkpoints/reporting_and_plotting-checkpoint.ipynb
pyqstrat-0.3.5.dist-info/LICENSE.txt
pyqstrat-0.3.5.dist-info/METADATA
pyqstrat-0.3.5.dist-info/WHEEL
pyqstrat-0.3.5.dist-info/top_level.txt
pyqstrat-0.3.5.dist-info/RECORD
