Metadata-Version: 2.1
Name: pyqstrat
Version: 0.3.5
Summary: fast / extensible library for backtesting quantitative strategies
Home-page: http://github.com/abbass2/pyqstrat/
Author: sal
Author-email: abbasi.sal@gmail.com
License: BSD
Platform: any
Classifier: Development Status :: 4 - Beta
Classifier: Natural Language :: English
Classifier: Intended Audience :: Developers
Classifier: License :: OSI Approved :: BSD License
Classifier: Operating System :: OS Independent
Classifier: Topic :: Software Development :: Libraries :: Python Modules
Classifier: Topic :: Software Development :: Libraries :: Application Frameworks
Classifier: Topic :: Office/Business :: Financial :: Investment
Classifier: Programming Language :: Python :: 3.6
Classifier: Programming Language :: Python :: 3 :: Only
Requires-Python: >=3.6
Requires-Dist: pandas (>=0.22)
Requires-Dist: numpy (>=1.14)
Requires-Dist: matplotlib (>=2.2.2)
Requires-Dist: scipy (>=1.0.0)
Requires-Dist: ipython (>=6.5.0)
Requires-Dist: pybind11 (>=2.2)
Requires-Dist: pyarrow (>=0.1.0)
Requires-Dist: sortedcontainers (>=2.0.5)
Provides-Extra: testing
Requires-Dist: pytest ; extra == 'testing'
